<loottables>
	<loottable name="NuggetSmall">
		<rewardLevel min="0" max="99">
			<advisors chance="20%">
				<rarity  common="33%" uncommon="34%" rare="33%" epic="0%" />
			</advisors>
			<materials chance="5%">
				<rarity junk="10%" uncommon="30%" common="30%" rare="30%" epic="0%" />
			</materials>
			<consumables chance="5%">
				<rarity  common="33%" uncommon="34%" rare="33%" epic="0%" />
			</consumables>
			<designs chance="10%">
				<rarity  common="33%" uncommon="34%" rare="33%" epic="0%" />
			</designs>
			<blueprints chance="10%">
				<rarity  common="33%" uncommon="34%" rare="33%" epic="0%" />
			</blueprints>
			<traits chance="50%">
				<rarity uncommon="33%" rare="34%" epic="33%" legendary="0%" />
			</traits>
		</rewardLevel>
	</loottable>
	<loottable name="NuggetMedium">
		<rewardLevel min="0" max="99">
			<advisors chance="20%">
				<rarity common="25%" uncommon="25%" rare="25%" epic="25%" />
			</advisors>
			<materials chance="5%">
				<rarity junk="0%" common="25%" uncommon="25%" rare="25%" epic="25%" />
			</materials>
			<consumables chance="5%">
				<rarity common="25%" uncommon="25%" rare="25%" epic="25%" />
			</consumables>
			<designs chance="10%">
				<rarity common="25%" uncommon="25%" rare="25%" epic="25%" />
			</designs>
			<blueprints chance="10%">
				<rarity common="25%" uncommon="25%" rare="25%" epic="25%" />
			</blueprints>
			<traits chance="50%">
				<rarity uncommon="33%" rare="34%" epic="33%" legendary="0%" />
			</traits>
		</rewardLevel>
	</loottable>
	<loottable name="NuggetLarge">
		<rewardLevel min="0" max="42">
			<advisors chance="20%">
				<rarity common="0%" uncommon="33%" rare="34%" epic="33%" />
			</advisors>
			<materials chance="5%">
				<rarity junk="0%" common="0%" uncommon="33%" rare="34%" epic="33%" />
			</materials>
			<consumables chance="5%">
				<rarity  common="0%" uncommon="33%" rare="34%" epic="33%" />
			</consumables>
			<designs chance="10%">
				<rarity common="0%" uncommon="33%" rare="34%" epic="33%" />
			</designs>
			<blueprints chance="10%">
				<rarity common="0%" uncommon="33%" rare="34%" epic="33%" />
			</blueprints>
			<traits chance="50%">
				<rarity uncommon="0%" rare="50%" epic="50%" legendary="0%" />
			</traits>
		</rewardLevel>
		<rewardLevel min="43" max="99">
			<advisors chance="20%">
				<rarity common="0%" uncommon="33%" rare="34%" epic="33%" />
			</advisors>
			<materials chance="5%">
				<rarity common="0%" junk="0%" uncommon="33%" rare="34%" epic="33%" />
			</materials>
			<consumables chance="5%">
				<rarity common="0%" uncommon="33%" rare="34%" epic="33%" />
			</consumables>
			<designs chance="10%">
				<rarity common="0%" uncommon="33%" rare="34%" epic="33%" />
			</designs>
			<blueprints chance="10%">
				<rarity common="0%" uncommon="33%" rare="34%" epic="33%" />
			</blueprints>
			<traits chance="50%">
				<rarity uncommon="0%" rare="49%" epic="50%" legendary="1%" />
			</traits>
		</rewardLevel>
	</loottable>
	<loottable name="NuggetLegendary">
		<rewardLevel min="0" max="99">
			<advisors chance="20%">
				<rarity common="0%" uncommon="0%" rare="50%" epic="50%" />
			</advisors>
			<materials chance="0%">
				<rarity uncommon="0%" junk="0%" common="0%" rare="0%" epic="0%" />
			</materials>
			<consumables chance="0%">
				<rarity common="0%" uncommon="0%" rare="0%" epic="0%" />
			</consumables>
			<designs chance="15%">
				<rarity common="0%" uncommon="0%" rare="50%" epic="50%" />
			</designs>
			<blueprints chance="15%">
				<rarity common="0%" uncommon="0%" rare="50%" epic="50%" />
			</blueprints>
			<traits chance="50%">
				<rarity uncommon="0%" rare="0%" epic="75%" legendary="25%" />
			</traits>
		</rewardLevel>
	</loottable>
</loottables>